odoo/addons/product_logistics_uom/README.rst
odoo/addons/product_logistics_uom/__init__.py
odoo/addons/product_logistics_uom/__manifest__.py
odoo/addons/product_logistics_uom/i18n/es.po
odoo/addons/product_logistics_uom/i18n/product_logistics_uom.pot
odoo/addons/product_logistics_uom/models/__init__.py
odoo/addons/product_logistics_uom/models/product_template.py
odoo/addons/product_logistics_uom/models/res_config_settings.py
odoo/addons/product_logistics_uom/readme/CONFIGURE.rst
odoo/addons/product_logistics_uom/readme/CONTRIBUTORS.rst
odoo/addons/product_logistics_uom/readme/CREDITS.rst
odoo/addons/product_logistics_uom/readme/DESCRIPTION.rst
odoo/addons/product_logistics_uom/readme/INSTALL.rst
odoo/addons/product_logistics_uom/static/description/icon.png
odoo/addons/product_logistics_uom/static/description/index.html
odoo/addons/product_logistics_uom/views/product.xml
odoo/addons/product_logistics_uom/views/res_config_settings.xml
odoo14_addon_product_logistics_uom-14.0.1.0.2.dist-info/METADATA
odoo14_addon_product_logistics_uom-14.0.1.0.2.dist-info/WHEEL
odoo14_addon_product_logistics_uom-14.0.1.0.2.dist-info/top_level.txt
odoo14_addon_product_logistics_uom-14.0.1.0.2.dist-info/RECORD
